README.md
setup.cfg
setup.py
Func3DCad/__init__.py
Func3DCad/core.py
Func3DCad/file_io.py
Func3DCad/render.py
Func3DCad/utils.py
Func3DCad.egg-info/PKG-INFO
Func3DCad.egg-info/SOURCES.txt
Func3DCad.egg-info/dependency_links.txt
Func3DCad.egg-info/not-zip-safe
Func3DCad.egg-info/top_level.txt