Metadata-Version: 2.1
Name: Func3DCad
Version: 1.3.2
Summary: A Python library for parametric 3D modeling and CAD operations.
Home-page: UNKNOWN
Author: sergey.winston
Author-email: sergey.winston@bk.ru
License: UNKNOWN
Platform: UNKNOWN
Classifier: Programming Language :: Python :: 3
Classifier: License :: OSI Approved :: MIT License
Classifier: Operating System :: OS Independent
